tailpipe.py
tailpipe-0.2.dist-info/entry_points.txt
tailpipe-0.2.dist-info/WHEEL
tailpipe-0.2.dist-info/METADATA
tailpipe-0.2.dist-info/RECORD
